LICENSE
README.rst
setup.py
tweetlimiter/__init__.py
tweetlimiter.egg-info/PKG-INFO
tweetlimiter.egg-info/SOURCES.txt
tweetlimiter.egg-info/dependency_links.txt
tweetlimiter.egg-info/requires.txt
tweetlimiter.egg-info/top_level.txt
tweetlimiter/tests/__init__.py
tweetlimiter/tests/test_main.py