Metadata-Version: 2.1
Name: tweetlimiter
Version: 0.1.0
Summary: Rate limit messages 
Home-page: https://gitlab.sauerburger.com/frank/tweetlimiter
Author: Frank Sauerburger
Author-email: frank@sauerburger.com
License: MIT
Classifier: Topic :: Communications
Classifier: Topic :: Scientific/Engineering :: Artificial Intelligence
License-File: LICENSE
